CHANGES
bootstrap.py
buildout.cfg
setup.cfg
setup.py
iw/__init__.py
iw.recipe.fss.egg-info/PKG-INFO
iw.recipe.fss.egg-info/SOURCES.txt
iw.recipe.fss.egg-info/dependency_links.txt
iw.recipe.fss.egg-info/entry_points.txt
iw.recipe.fss.egg-info/namespace_packages.txt
iw.recipe.fss.egg-info/not-zip-safe
iw.recipe.fss.egg-info/requires.txt
iw.recipe.fss.egg-info/top_level.txt
iw/recipe/__init__.py
iw/recipe/fss/CHANGES
iw/recipe/fss/README.txt
iw/recipe/fss/__init__.py
iw/recipe/fss/docs/README.txt
iw/recipe/fss/doctests/README.txt
iw/recipe/fss/tests/__init__.py
iw/recipe/fss/tests/test_fssdocs.py