Metadata-Version: 1.0
Name: iw.recipe.fss
Version: 0.2.0
Summary: Recipe to configure File System Storage
Home-page: http://ingeniweb.svn.sourceforge.net/viewvc/ingeniweb/iw.recipe.fss
Author: Ingeniweb
Author-email: support@ingeniweb.com
License: GPL
Keywords: recipe zope plone fss
Platform: UNKNOWN
Classifier: Programming Language :: Python
Classifier: Topic :: Software Development :: Libraries :: Python Modules
